moxtrice/__init__.py
moxtrice/_version.py
moxtrice/config.py
moxtrice/core.py
moxtrice/main.py
moxtrice/utils.py
moxtrice-1.1.1.dev0.dist-info/licenses/LICENSE
moxtrice-1.1.1.dev0.dist-info/METADATA
moxtrice-1.1.1.dev0.dist-info/WHEEL
moxtrice-1.1.1.dev0.dist-info/entry_points.txt
moxtrice-1.1.1.dev0.dist-info/top_level.txt
moxtrice-1.1.1.dev0.dist-info/RECORD
