Metadata-Version: 2.4
Name: moxtrice
Version: 1.1.1.dev0
Summary: A simple tool to synchronize between moxfield.com and cockatrice
Author-email: Xie Zejian <xiezej@gmail.com>
License:                                  Apache License
Project-URL: Homepage, https://github.com/fecet/moxtrice
Project-URL: Bug Tracker, https://github.com/fecet/moxtrice/issues
Classifier: Programming Language :: Python :: 3
Classifier: License :: OSI Approved :: Apache Software License
License-File: LICENSE
Requires-Dist: requests
Requires-Dist: emoji
Requires-Dist: ml_collections
Requires-Dist: tqdm
Requires-Dist: pathvalidate
Requires-Dist: curl_cffi
Dynamic: license-file
